{"title":"单片机学习之旅","uid":"9bf5dc2db74bc1e3a8043670690f028e","slug":"单片机学习之旅","date":"2021-08-06T08:42:29.000Z","updated":"2021-08-06T10:30:56.514Z","comments":true,"path":"api/articles/单片机学习之旅.json","keywords":null,"cover":[],"content":"<p>本文记录个人学习单片机的学习过程，部分内容可能有些许不正确，参考时需甄别.</p>\n<h3 id=\"定时器\"><a href=\"#定时器\" class=\"headerlink\" title=\"定时器\"></a>定时器</h3><p><b>定时器</b>是单片机的内部资源，其电路的链接和运转均在单片机内部完成；其一个重要的意义就是再单片机进行计时的时候，是可以运作其他工作的，大大提高了单片机的运行效率；</p>\n<h4 id=\"了解定时器的工作原理\"><a href=\"#了解定时器的工作原理\" class=\"headerlink\" title=\"了解定时器的工作原理\"></a>了解定时器的工作原理</h4><p><img src=\"../images/blog/Snipaste_2021-08-06_17-13-15.png\"></p>\n<p>由第一部分产生时间脉冲，每次时间脉冲到来，第二部分进行计数加一，当发生溢出的时候进而产生中断信号，然后执行相应的功能(以上是<code>T0</code>模式)；</p>\n<p><b>SYSclk</b>是系统时钟(12MHz)，会经过12分频/1分频到下一阶段；</p>\n<p><svg xmlns:xlink=\"http://www.w3.org/1999/xlink\" width=\"4.861ex\" height=\"3.509ex\" style=\"vertical-align: -0.838ex;\" viewBox=\"0 -1150.1 2093 1510.9\" role=\"img\" focusable=\"false\" xmlns=\"http://www.w3.org/2000/svg\" aria-labelledby=\"MathJax-SVG-1-Title\">\n<title id=\"MathJax-SVG-1-Title\">C/\\overline{T}</title>\n<defs aria-hidden=\"true\">\n<path stroke-width=\"1\" id=\"E1-MJMATHI-43\" d=\"M50 252Q50 367 117 473T286 641T490 704Q580 704 633 653Q642 643 648 636T656 626L657 623Q660 623 684 649Q691 655 699 663T715 679T725 690L740 705H746Q760 705 760 698Q760 694 728 561Q692 422 692 421Q690 416 687 415T669 413H653Q647 419 647 422Q647 423 648 429T650 449T651 481Q651 552 619 605T510 659Q484 659 454 652T382 628T299 572T226 479Q194 422 175 346T156 222Q156 108 232 58Q280 24 350 24Q441 24 512 92T606 240Q610 253 612 255T628 257Q648 257 648 248Q648 243 647 239Q618 132 523 55T319 -22Q206 -22 128 53T50 252Z\"></path>\n<path stroke-width=\"1\" id=\"E1-MJMAIN-2F\" d=\"M423 750Q432 750 438 744T444 730Q444 725 271 248T92 -240Q85 -250 75 -250Q68 -250 62 -245T56 -231Q56 -221 230 257T407 740Q411 750 423 750Z\"></path>\n<path stroke-width=\"1\" id=\"E1-MJMATHI-54\" d=\"M40 437Q21 437 21 445Q21 450 37 501T71 602L88 651Q93 669 101 677H569H659Q691 677 697 676T704 667Q704 661 687 553T668 444Q668 437 649 437Q640 437 637 437T631 442L629 445Q629 451 635 490T641 551Q641 586 628 604T573 629Q568 630 515 631Q469 631 457 630T439 622Q438 621 368 343T298 60Q298 48 386 46Q418 46 427 45T436 36Q436 31 433 22Q429 4 424 1L422 0Q419 0 415 0Q410 0 363 1T228 2Q99 2 64 0H49Q43 6 43 9T45 27Q49 40 55 46H83H94Q174 46 189 55Q190 56 191 56Q196 59 201 76T241 233Q258 301 269 344Q339 619 339 625Q339 630 310 630H279Q212 630 191 624Q146 614 121 583T67 467Q60 445 57 441T43 437H40Z\"></path>\n<path stroke-width=\"1\" id=\"E1-MJMAIN-AF\" d=\"M69 544V590H430V544H69Z\"></path>\n</defs>\n<g stroke=\"currentColor\" fill=\"currentColor\" stroke-width=\"0\" transform=\"matrix(1 0 0 -1 0 0)\" aria-hidden=\"true\">\n <use xlink:href=\"#E1-MJMATHI-43\" x=\"0\" y=\"0\"></use>\n <use xlink:href=\"#E1-MJMAIN-2F\" x=\"760\" y=\"0\"></use>\n<g transform=\"translate(1261,0)\">\n <use xlink:href=\"#E1-MJMATHI-54\" x=\"24\" y=\"0\"></use>\n<g transform=\"translate(78,494)\">\n <use transform=\"scale(0.707)\" xlink:href=\"#E1-MJMAIN-AF\" x=\"-70\" y=\"0\"></use>\n<g transform=\"translate(217.922504166681,0) scale(0.7598710656283806,1)\">\n <use transform=\"scale(0.707)\" xlink:href=\"#E1-MJMAIN-AF\"></use>\n</g>\n <use transform=\"scale(0.707)\" xlink:href=\"#E1-MJMAIN-AF\" x=\"565\" y=\"0\"></use>\n</g>\n</g>\n</g>\n</svg>则是用来决定定时器模式还是计时器模型，为1时表示时计数器的模式，为0时表示它是定时器模型</p>\n<h4 id=\"初识中断系统\"><a href=\"#初识中断系统\" class=\"headerlink\" title=\"初识中断系统\"></a>初识中断系统</h4><p><b>终端系统</b>是为<code>CPU</code>具有对外界紧急事件的实时处理能力设置的；当<code>CPU</code>正在处理某件事的时候发生了紧急事件的请求，要求<code>CPU</code>暂停当亲的工作，转而去处理这个紧急事件，<b>处理完以后，再回到原来被中断的地方，继续原来的工作</b>，这样的过程称为<strong>中断</strong>；</p>\n<p>还需要注意的是，中断是有优先级的，不同的中断一般具有不同的优先级，高优先级的中断能够打断低优先级的中断；这个中断的概念和<b>计算机系统</b>的中断时等同的；</p>\n<h4 id=\"定时器相关的寄存器\"><a href=\"#定时器相关的寄存器\" class=\"headerlink\" title=\"定时器相关的寄存器\"></a>定时器相关的寄存器</h4><p><img src=\"../images/blog/Snipaste_2021-08-06_18-28-40.png\"></p>\n","text":"本文记录个人学习单片机的学习过程，部分内容可能有些许不正确，参考时需甄别. 定时器定时器是单片机的内部资源，其电路的链接和运转均在单片机内部完成；其一个重要的意义就是再单片机进行计时的时候，是可以运作其他工作的，大大提高了单片机的运行效率； 了解定时器的工作原理 由第一部分产生时...","link":"","photos":[],"count_time":{"symbolsCount":531,"symbolsTime":"1 mins."},"categories":[{"name":"单片机","slug":"单片机","count":1,"path":"api/categories/单片机.json"}],"tags":[{"name":"STC单片机","slug":"STC单片机","count":1,"path":"api/tags/STC单片机.json"}],"toc":"<ol class=\"toc\"><li class=\"toc-item toc-level-3\"><a class=\"toc-link\" href=\"#%E5%AE%9A%E6%97%B6%E5%99%A8\"><span class=\"toc-text\">定时器</span></a><ol class=\"toc-child\"><li class=\"toc-item toc-level-4\"><a class=\"toc-link\" href=\"#%E4%BA%86%E8%A7%A3%E5%AE%9A%E6%97%B6%E5%99%A8%E7%9A%84%E5%B7%A5%E4%BD%9C%E5%8E%9F%E7%90%86\"><span class=\"toc-text\">了解定时器的工作原理</span></a></li><li class=\"toc-item toc-level-4\"><a class=\"toc-link\" href=\"#%E5%88%9D%E8%AF%86%E4%B8%AD%E6%96%AD%E7%B3%BB%E7%BB%9F\"><span class=\"toc-text\">初识中断系统</span></a></li><li class=\"toc-item toc-level-4\"><a class=\"toc-link\" href=\"#%E5%AE%9A%E6%97%B6%E5%99%A8%E7%9B%B8%E5%85%B3%E7%9A%84%E5%AF%84%E5%AD%98%E5%99%A8\"><span class=\"toc-text\">定时器相关的寄存器</span></a></li></ol></li></ol>","author":{"name":"Dominique Yiu","slug":"blog-author","avatar":"https://gitee.com/dominique-yiu/csdn/raw/master/theme/icon.png","link":"/","description":"There is only one heroism in the world, to see the world as it is and to love it. <br /> @ <b>realrealyiu@gmail.com</b>","socials":{"github":"https://github.com/Dominique-Yiu","twitter":"https://twitter.com/KingSwi39106371","stackoverflow":"","wechat":"","qq":"","weibo":"","zhihu":"https://www.zhihu.com/people/whatever-36-86","csdn":"https://blog.csdn.net/qq_49005782","juejin":"","customs":{}}},"mapped":true,"prev_post":{"title":"哈希表","uid":"52296d4e1e538f3ec200aa2ca9533c17","slug":"哈希表","date":"2021-08-09T04:01:28.000Z","updated":"2021-08-09T06:22:39.634Z","comments":true,"path":"api/articles/哈希表.json","keywords":null,"cover":"/images/theme/20210809.jpg","text":"哈希表 哈希表是一种数据结构，它使用哈希函数组织数据， 以支持快速插入和搜索. 哈希表的原理 哈希表的关键思想是使用哈希函数将键映射到储存桶.(其实可以简单的对应数学函数的映射) 当插入一个新的键时，哈希函数将决定该键应该分配到哪个桶中，并将该键储存在相应的桶中； 如果需要搜索一...","link":"","photos":[],"count_time":{"symbolsCount":324,"symbolsTime":"1 mins."},"categories":[{"name":"哈希表","slug":"哈希表","count":1,"path":"api/categories/哈希表.json"}],"tags":[{"name":"hash table","slug":"hash-table","count":1,"path":"api/tags/hash-table.json"}],"author":{"name":"Dominique Yiu","slug":"blog-author","avatar":"https://gitee.com/dominique-yiu/csdn/raw/master/theme/icon.png","link":"/","description":"There is only one heroism in the world, to see the world as it is and to love it. <br /> @ <b>realrealyiu@gmail.com</b>","socials":{"github":"https://github.com/Dominique-Yiu","twitter":"https://twitter.com/KingSwi39106371","stackoverflow":"","wechat":"","qq":"","weibo":"","zhihu":"https://www.zhihu.com/people/whatever-36-86","csdn":"https://blog.csdn.net/qq_49005782","juejin":"","customs":{}}}},"next_post":{"title":"深度优先算法","uid":"07581150a57deadf8be9c70c2b10bcb4","slug":"深度优先算法","date":"2021-08-06T03:25:54.000Z","updated":"2021-08-07T14:59:31.732Z","comments":true,"path":"api/articles/深度优先算法.json","keywords":null,"cover":"./images/theme/20210806.jpg","text":"深度优先深度优先搜索算法（英语：Depth-First-Search，DFS）是一种用于遍历或搜索树或图的算法。其过程简要来说是对每一个可能的分支路径深入到不能再深入为止，而且每个结点只能访问一次. 虽然出现的频率不是特别高但是也是一个非常重要的只是好点. 二叉树的中序遍历这个题...","link":"","photos":[],"count_time":{"symbolsCount":"1.7k","symbolsTime":"2 mins."},"categories":[{"name":"深度优先","slug":"深度优先","count":1,"path":"api/categories/深度优先.json"}],"tags":[{"name":"DFS","slug":"DFS","count":1,"path":"api/tags/DFS.json"}],"author":{"name":"Dominique Yiu","slug":"blog-author","avatar":"https://gitee.com/dominique-yiu/csdn/raw/master/theme/icon.png","link":"/","description":"There is only one heroism in the world, to see the world as it is and to love it. <br /> @ <b>realrealyiu@gmail.com</b>","socials":{"github":"https://github.com/Dominique-Yiu","twitter":"https://twitter.com/KingSwi39106371","stackoverflow":"","wechat":"","qq":"","weibo":"","zhihu":"https://www.zhihu.com/people/whatever-36-86","csdn":"https://blog.csdn.net/qq_49005782","juejin":"","customs":{}}}}}