{"name":"Softmax","slug":"Softmax","count":1,"postlist":[{"title":"Softmax回归","uid":"d2d60baf6716ca9f3f193bfd072d2f20","slug":"Softmax回归","date":"2021-07-30T13:32:46.000Z","updated":"2021-07-30T14:06:56.549Z","comments":true,"path":"api/articles/Softmax回归.json","keywords":null,"cover":null,"text":"","link":"","photos":[],"count_time":{"symbolsCount":0,"symbolsTime":"1 mins."},"categories":[{"name":"深度学习","slug":"深度学习","count":1,"path":"api/categories/深度学习.json"}],"tags":[{"name":"Softmax","slug":"Softmax","count":1,"path":"api/tags/Softmax.json"}],"author":{"name":"Dominique Yiu","slug":"blog-author","avatar":"https://gitee.com/dominique-yiu/csdn/raw/master/theme/icon.png","link":"/","description":"There is only one heroism in the world, to see the world as it is and to love it. <br /> @ <b>realrealyiu@gmail.com</b>","socials":{"github":"https://github.com/Dominique-Yiu","twitter":"https://twitter.com/KingSwi39106371","stackoverflow":"","wechat":"","qq":"","weibo":"","zhihu":"https://www.zhihu.com/people/whatever-36-86","csdn":"https://blog.csdn.net/qq_49005782","juejin":"","customs":{}}}}]}